setup.py
pypimath2/__init__.py
sn2264.egg-info/PKG-INFO
sn2264.egg-info/SOURCES.txt
sn2264.egg-info/dependency_links.txt
sn2264.egg-info/top_level.txt