Metadata-Version: 1.0
Name: sn2264
Version: 0.0.1
Summary: example pypi proj
Home-page: UNKNOWN
Author: UNKNOWN
Author-email: UNKNOWN
License: UNKNOWN
Platform: UNKNOWN
